<?xml version="1.0" ?>
<XmlSauvExportAperoGlob>
     <Iters>
          <OneIm>
               <Name>Crop-IMG_PHR1A_P_201406121049025.tif</Name>
               <Residual>2.11241215159907725</Residual>
               <PercOk>50</PercOk>
               <NbPts>384</NbPts>
               <NbPtsMul>0</NbPtsMul>
          </OneIm>
          <OneIm>
               <Name>Crop-IMG_PHR1A_P_201406121049386.tif</Name>
               <Residual>2.05096548686862912</Residual>
               <PercOk>37.7358490566037759</PercOk>
               <NbPts>371</NbPts>
               <NbPtsMul>0</NbPtsMul>
          </OneIm>
          <OneIm>
               <Name>OIS-Reech_IGNF_PVA_1-0__1971-06-21__C2844-0141_1971_FR2117_1066.tif</Name>
               <Residual>0.76156287382108856</Residual>
               <PercOk>73.7623762376237693</PercOk>
               <NbPts>202</NbPts>
               <NbPtsMul>55</NbPtsMul>
          </OneIm>
          <OneIm>
               <Name>OIS-Reech_IGNF_PVA_1-0__1971-06-21__C2844-0141_1971_FR2117_1067.tif</Name>
               <Residual>0.457982954122367392</Residual>
               <PercOk>70.2265372168284756</PercOk>
               <NbPts>309</NbPts>
               <NbPtsMul>86</NbPtsMul>
          </OneIm>
          <OneIm>
               <Name>OIS-Reech_IGNF_PVA_1-0__1971-06-21__C2844-0141_1971_FR2117_1068.tif</Name>
               <Residual>0.406372779372494164</Residual>
               <PercOk>82.3529411764705941</PercOk>
               <NbPts>153</NbPts>
               <NbPtsMul>32</NbPtsMul>
          </OneIm>
          <OneIm>
               <Name>OIS-Reech_IGNF_PVA_1-0__1971-06-21__C2844-0141_1971_FR2117_1122.tif</Name>
               <Residual>0.615923468204360947</Residual>
               <PercOk>76.7676767676767611</PercOk>
               <NbPts>198</NbPts>
               <NbPtsMul>49</NbPtsMul>
          </OneIm>
          <OneIm>
               <Name>OIS-Reech_IGNF_PVA_1-0__1971-06-21__C2844-0141_1971_FR2117_1123.tif</Name>
               <Residual>0.96840944959527131</Residual>
               <PercOk>86.1111111111111143</PercOk>
               <NbPts>360</NbPts>
               <NbPtsMul>88</NbPtsMul>
          </OneIm>
          <OneIm>
               <Name>OIS-Reech_IGNF_PVA_1-0__1971-06-21__C2844-0141_1971_FR2117_1124.tif</Name>
               <Residual>1.23285385935847147</Residual>
               <PercOk>73.8675958188153317</PercOk>
               <NbPts>287</NbPts>
               <NbPtsMul>92</NbPtsMul>
          </OneIm>
          <AverageResidual>1.24803430334963705</AverageResidual>
          <NumIter>0</NumIter>
          <NumEtape>0</NumEtape>
     </Iters>
     <Iters>
          <OneIm>
               <Name>Crop-IMG_PHR1A_P_201406121049025.tif</Name>
               <Residual>2.05504718786950402</Residual>
               <PercOk>51.3020833333333357</PercOk>
               <NbPts>384</NbPts>
               <NbPtsMul>0</NbPtsMul>
          </OneIm>
          <OneIm>
               <Name>Crop-IMG_PHR1A_P_201406121049386.tif</Name>
               <Residual>2.04912182006813781</Residual>
               <PercOk>44.474393530997304</PercOk>
               <NbPts>371</NbPts>
               <NbPtsMul>0</NbPtsMul>
          </OneIm>
          <OneIm>
               <Name>OIS-Reech_IGNF_PVA_1-0__1971-06-21__C2844-0141_1971_FR2117_1066.tif</Name>
               <Residual>0.756881552187258944</Residual>
               <PercOk>74.2574257425742559</PercOk>
               <NbPts>202</NbPts>
               <NbPtsMul>55</NbPtsMul>
          </OneIm>
          <OneIm>
               <Name>OIS-Reech_IGNF_PVA_1-0__1971-06-21__C2844-0141_1971_FR2117_1067.tif</Name>
               <Residual>0.485313918975880887</Residual>
               <PercOk>70.2265372168284756</PercOk>
               <NbPts>309</NbPts>
               <NbPtsMul>86</NbPtsMul>
          </OneIm>
          <OneIm>
               <Name>OIS-Reech_IGNF_PVA_1-0__1971-06-21__C2844-0141_1971_FR2117_1068.tif</Name>
               <Residual>0.390398801307433874</Residual>
               <PercOk>82.3529411764705941</PercOk>
               <NbPts>153</NbPts>
               <NbPtsMul>32</NbPtsMul>
          </OneIm>
          <OneIm>
               <Name>OIS-Reech_IGNF_PVA_1-0__1971-06-21__C2844-0141_1971_FR2117_1122.tif</Name>
               <Residual>0.705886663196581332</Residual>
               <PercOk>79.7979797979797922</PercOk>
               <NbPts>198</NbPts>
               <NbPtsMul>49</NbPtsMul>
          </OneIm>
          <OneIm>
               <Name>OIS-Reech_IGNF_PVA_1-0__1971-06-21__C2844-0141_1971_FR2117_1123.tif</Name>
               <Residual>1.01895921235931852</Residual>
               <PercOk>88.6111111111111143</PercOk>
               <NbPts>360</NbPts>
               <NbPtsMul>88</NbPtsMul>
          </OneIm>
          <OneIm>
               <Name>OIS-Reech_IGNF_PVA_1-0__1971-06-21__C2844-0141_1971_FR2117_1124.tif</Name>
               <Residual>1.30486661595308506</Residual>
               <PercOk>76.6550522648083614</PercOk>
               <NbPts>287</NbPts>
               <NbPtsMul>92</NbPtsMul>
          </OneIm>
          <AverageResidual>1.25609317076126459</AverageResidual>
          <NumIter>1</NumIter>
          <NumEtape>0</NumEtape>
          <EvolMax>0.00441649992875239178</EvolMax>
          <EvolMoy>0.00116666696950281355</EvolMoy>
     </Iters>
     <Iters>
          <OneIm>
               <Name>Crop-IMG_PHR1A_P_201406121049025.tif</Name>
               <Residual>1.89641322020343273</Residual>
               <PercOk>57.5520833333333357</PercOk>
               <NbPts>384</NbPts>
               <NbPtsMul>0</NbPtsMul>
          </OneIm>
          <OneIm>
               <Name>Crop-IMG_PHR1A_P_201406121049386.tif</Name>
               <Residual>1.99101602434995439</Residual>
               <PercOk>57.1428571428571459</PercOk>
               <NbPts>371</NbPts>
               <NbPtsMul>0</NbPtsMul>
          </OneIm>
          <OneIm>
               <Name>OIS-Reech_IGNF_PVA_1-0__1971-06-21__C2844-0141_1971_FR2117_1066.tif</Name>
               <Residual>0.70254649284326709</Residual>
               <PercOk>74.7524752475247567</PercOk>
               <NbPts>202</NbPts>
               <NbPtsMul>55</NbPtsMul>
          </OneIm>
          <OneIm>
               <Name>OIS-Reech_IGNF_PVA_1-0__1971-06-21__C2844-0141_1971_FR2117_1067.tif</Name>
               <Residual>0.535965096762384352</Residual>
               <PercOk>72.1682847896440194</PercOk>
               <NbPts>309</NbPts>
               <NbPtsMul>86</NbPtsMul>
          </OneIm>
          <OneIm>
               <Name>OIS-Reech_IGNF_PVA_1-0__1971-06-21__C2844-0141_1971_FR2117_1068.tif</Name>
               <Residual>0.422623906697475293</Residual>
               <PercOk>83.0065359477124218</PercOk>
               <NbPts>153</NbPts>
               <NbPtsMul>32</NbPtsMul>
          </OneIm>
          <OneIm>
               <Name>OIS-Reech_IGNF_PVA_1-0__1971-06-21__C2844-0141_1971_FR2117_1122.tif</Name>
               <Residual>0.813324160110144412</Residual>
               <PercOk>84.343434343434339</PercOk>
               <NbPts>198</NbPts>
               <NbPtsMul>49</NbPtsMul>
          </OneIm>
          <OneIm>
               <Name>OIS-Reech_IGNF_PVA_1-0__1971-06-21__C2844-0141_1971_FR2117_1123.tif</Name>
               <Residual>1.04521741519498801</Residual>
               <PercOk>94.1666666666666714</PercOk>
               <NbPts>360</NbPts>
               <NbPtsMul>88</NbPtsMul>
          </OneIm>
          <OneIm>
               <Name>OIS-Reech_IGNF_PVA_1-0__1971-06-21__C2844-0141_1971_FR2117_1124.tif</Name>
               <Residual>1.41885345879926938</Residual>
               <PercOk>86.4111498257839656</PercOk>
               <NbPts>287</NbPts>
               <NbPtsMul>92</NbPtsMul>
          </OneIm>
          <AverageResidual>1.23930876948801516</AverageResidual>
          <NumIter>2</NumIter>
          <NumEtape>0</NumEtape>
          <EvolMax>0.0117676991397567023</EvolMax>
          <EvolMoy>0.00159435866715298643</EvolMoy>
     </Iters>
     <Iters>
          <OneIm>
               <Name>Crop-IMG_PHR1A_P_201406121049025.tif</Name>
               <Residual>1.85361824376455586</Residual>
               <PercOk>64.3229166666666714</PercOk>
               <NbPts>384</NbPts>
               <NbPtsMul>0</NbPtsMul>
          </OneIm>
          <OneIm>
               <Name>Crop-IMG_PHR1A_P_201406121049386.tif</Name>
               <Residual>1.92287626315949645</Residual>
               <PercOk>68.4636118598382808</PercOk>
               <NbPts>371</NbPts>
               <NbPtsMul>0</NbPtsMul>
          </OneIm>
          <OneIm>
               <Name>OIS-Reech_IGNF_PVA_1-0__1971-06-21__C2844-0141_1971_FR2117_1066.tif</Name>
               <Residual>0.771564039054764339</Residual>
               <PercOk>76.7326732673267315</PercOk>
               <NbPts>202</NbPts>
               <NbPtsMul>55</NbPtsMul>
          </OneIm>
          <OneIm>
               <Name>OIS-Reech_IGNF_PVA_1-0__1971-06-21__C2844-0141_1971_FR2117_1067.tif</Name>
               <Residual>0.665613572120255959</Residual>
               <PercOk>75.4045307443365687</PercOk>
               <NbPts>309</NbPts>
               <NbPtsMul>86</NbPtsMul>
          </OneIm>
          <OneIm>
               <Name>OIS-Reech_IGNF_PVA_1-0__1971-06-21__C2844-0141_1971_FR2117_1068.tif</Name>
               <Residual>0.393197054700285098</Residual>
               <PercOk>83.0065359477124218</PercOk>
               <NbPts>153</NbPts>
               <NbPtsMul>32</NbPtsMul>
          </OneIm>
          <OneIm>
               <Name>OIS-Reech_IGNF_PVA_1-0__1971-06-21__C2844-0141_1971_FR2117_1122.tif</Name>
               <Residual>0.882334126241040906</Residual>
               <PercOk>88.3838383838383805</PercOk>
               <NbPts>198</NbPts>
               <NbPtsMul>49</NbPtsMul>
          </OneIm>
          <OneIm>
               <Name>OIS-Reech_IGNF_PVA_1-0__1971-06-21__C2844-0141_1971_FR2117_1123.tif</Name>
               <Residual>1.00648015283681036</Residual>
               <PercOk>96.1111111111111143</PercOk>
               <NbPts>360</NbPts>
               <NbPtsMul>88</NbPtsMul>
          </OneIm>
          <OneIm>
               <Name>OIS-Reech_IGNF_PVA_1-0__1971-06-21__C2844-0141_1971_FR2117_1124.tif</Name>
               <Residual>1.37088474913517522</Residual>
               <PercOk>91.6376306620209107</PercOk>
               <NbPts>287</NbPts>
               <NbPtsMul>92</NbPtsMul>
          </OneIm>
          <AverageResidual>1.22459947219552956</AverageResidual>
          <NumIter>3</NumIter>
          <NumEtape>0</NumEtape>
          <EvolMax>0.00710150088819150229</EvolMax>
          <EvolMoy>0.000887518321595836884</EvolMoy>
     </Iters>
     <Iters>
          <OneIm>
               <Name>Crop-IMG_PHR1A_P_201406121049025.tif</Name>
               <Residual>1.79843252885954441</Residual>
               <PercOk>70.0520833333333286</PercOk>
               <NbPts>384</NbPts>
               <NbPtsMul>0</NbPtsMul>
          </OneIm>
          <OneIm>
               <Name>Crop-IMG_PHR1A_P_201406121049386.tif</Name>
               <Residual>1.75151074127261763</Residual>
               <PercOk>74.6630727762803303</PercOk>
               <NbPts>371</NbPts>
               <NbPtsMul>0</NbPtsMul>
          </OneIm>
          <OneIm>
               <Name>OIS-Reech_IGNF_PVA_1-0__1971-06-21__C2844-0141_1971_FR2117_1066.tif</Name>
               <Residual>0.858644303692342459</Residual>
               <PercOk>79.702970297029708</PercOk>
               <NbPts>202</NbPts>
               <NbPtsMul>55</NbPtsMul>
          </OneIm>
          <OneIm>
               <Name>OIS-Reech_IGNF_PVA_1-0__1971-06-21__C2844-0141_1971_FR2117_1067.tif</Name>
               <Residual>0.778998742658280285</Residual>
               <PercOk>80.2588996763754068</PercOk>
               <NbPts>309</NbPts>
               <NbPtsMul>86</NbPtsMul>
          </OneIm>
          <OneIm>
               <Name>OIS-Reech_IGNF_PVA_1-0__1971-06-21__C2844-0141_1971_FR2117_1068.tif</Name>
               <Residual>0.473738374392114414</Residual>
               <PercOk>84.3137254901960773</PercOk>
               <NbPts>153</NbPts>
               <NbPtsMul>32</NbPtsMul>
          </OneIm>
          <OneIm>
               <Name>OIS-Reech_IGNF_PVA_1-0__1971-06-21__C2844-0141_1971_FR2117_1122.tif</Name>
               <Residual>0.842226333380159398</Residual>
               <PercOk>89.8989898989898961</PercOk>
               <NbPts>198</NbPts>
               <NbPtsMul>49</NbPtsMul>
          </OneIm>
          <OneIm>
               <Name>OIS-Reech_IGNF_PVA_1-0__1971-06-21__C2844-0141_1971_FR2117_1123.tif</Name>
               <Residual>0.964775832236816622</Residual>
               <PercOk>96.3888888888888857</PercOk>
               <NbPts>360</NbPts>
               <NbPtsMul>88</NbPtsMul>
          </OneIm>
          <OneIm>
               <Name>OIS-Reech_IGNF_PVA_1-0__1971-06-21__C2844-0141_1971_FR2117_1124.tif</Name>
               <Residual>1.3146686381355992</Residual>
               <PercOk>93.3797909407665543</PercOk>
               <NbPts>287</NbPts>
               <NbPtsMul>92</NbPtsMul>
          </OneIm>
          <AverageResidual>1.1852836051741058</AverageResidual>
          <NumIter>4</NumIter>
          <NumEtape>0</NumEtape>
          <EvolMax>0.00584212116134647484</EvolMax>
          <EvolMoy>0.000739186130681117911</EvolMoy>
     </Iters>
     <Iters>
          <OneIm>
               <Name>Crop-IMG_PHR1A_P_201406121049025.tif</Name>
               <Residual>1.81085082126130237</Residual>
               <PercOk>78.6458333333333286</PercOk>
               <NbPts>384</NbPts>
               <NbPtsMul>0</NbPtsMul>
          </OneIm>
          <OneIm>
               <Name>Crop-IMG_PHR1A_P_201406121049386.tif</Name>
               <Residual>1.7303570031745803</Residual>
               <PercOk>81.1320754716981156</PercOk>
               <NbPts>371</NbPts>
               <NbPtsMul>0</NbPtsMul>
          </OneIm>
          <OneIm>
               <Name>OIS-Reech_IGNF_PVA_1-0__1971-06-21__C2844-0141_1971_FR2117_1066.tif</Name>
               <Residual>1.01085061390054931</Residual>
               <PercOk>87.128712871287135</PercOk>
               <NbPts>202</NbPts>
               <NbPtsMul>55</NbPtsMul>
          </OneIm>
          <OneIm>
               <Name>OIS-Reech_IGNF_PVA_1-0__1971-06-21__C2844-0141_1971_FR2117_1067.tif</Name>
               <Residual>0.987918633673563362</Residual>
               <PercOk>88.3495145631067942</PercOk>
               <NbPts>309</NbPts>
               <NbPtsMul>86</NbPtsMul>
          </OneIm>
          <OneIm>
               <Name>OIS-Reech_IGNF_PVA_1-0__1971-06-21__C2844-0141_1971_FR2117_1068.tif</Name>
               <Residual>0.644431642351433465</Residual>
               <PercOk>87.5816993464052302</PercOk>
               <NbPts>153</NbPts>
               <NbPtsMul>32</NbPtsMul>
          </OneIm>
          <OneIm>
               <Name>OIS-Reech_IGNF_PVA_1-0__1971-06-21__C2844-0141_1971_FR2117_1122.tif</Name>
               <Residual>0.798565749981220763</Residual>
               <PercOk>90.4040404040404013</PercOk>
               <NbPts>198</NbPts>
               <NbPtsMul>49</NbPtsMul>
          </OneIm>
          <OneIm>
               <Name>OIS-Reech_IGNF_PVA_1-0__1971-06-21__C2844-0141_1971_FR2117_1123.tif</Name>
               <Residual>0.945369167338059202</Residual>
               <PercOk>96.3888888888888857</PercOk>
               <NbPts>360</NbPts>
               <NbPtsMul>88</NbPtsMul>
          </OneIm>
          <OneIm>
               <Name>OIS-Reech_IGNF_PVA_1-0__1971-06-21__C2844-0141_1971_FR2117_1124.tif</Name>
               <Residual>1.29076230392326341</Residual>
               <PercOk>94.4250871080139405</PercOk>
               <NbPts>287</NbPts>
               <NbPtsMul>92</NbPtsMul>
          </OneIm>
          <AverageResidual>1.21880616958615429</AverageResidual>
          <NumIter>5</NumIter>
          <NumEtape>0</NumEtape>
          <EvolMax>0.00501324927174671194</EvolMax>
          <EvolMoy>0.000700149868292726301</EvolMoy>
     </Iters>
     <Iters>
          <OneIm>
               <Name>Crop-IMG_PHR1A_P_201406121049025.tif</Name>
               <Residual>1.76986964660130064</Residual>
               <PercOk>85.15625</PercOk>
               <NbPts>384</NbPts>
               <NbPtsMul>0</NbPtsMul>
          </OneIm>
          <OneIm>
               <Name>Crop-IMG_PHR1A_P_201406121049386.tif</Name>
               <Residual>1.6757860338680588</Residual>
               <PercOk>85.1752021563342367</PercOk>
               <NbPts>371</NbPts>
               <NbPtsMul>0</NbPtsMul>
          </OneIm>
          <OneIm>
               <Name>OIS-Reech_IGNF_PVA_1-0__1971-06-21__C2844-0141_1971_FR2117_1066.tif</Name>
               <Residual>1.08001594847401794</Residual>
               <PercOk>93.0693069306930738</PercOk>
               <NbPts>202</NbPts>
               <NbPtsMul>55</NbPtsMul>
          </OneIm>
          <OneIm>
               <Name>OIS-Reech_IGNF_PVA_1-0__1971-06-21__C2844-0141_1971_FR2117_1067.tif</Name>
               <Residual>1.08830174619823605</Residual>
               <PercOk>94.8220064724919069</PercOk>
               <NbPts>309</NbPts>
               <NbPtsMul>86</NbPtsMul>
          </OneIm>
          <OneIm>
               <Name>OIS-Reech_IGNF_PVA_1-0__1971-06-21__C2844-0141_1971_FR2117_1068.tif</Name>
               <Residual>0.666136621038777244</Residual>
               <PercOk>90.1960784313725554</PercOk>
               <NbPts>153</NbPts>
               <NbPtsMul>32</NbPtsMul>
          </OneIm>
          <OneIm>
               <Name>OIS-Reech_IGNF_PVA_1-0__1971-06-21__C2844-0141_1971_FR2117_1122.tif</Name>
               <Residual>0.814415459744075698</Residual>
               <PercOk>90.9090909090909065</PercOk>
               <NbPts>198</NbPts>
               <NbPtsMul>49</NbPtsMul>
          </OneIm>
          <OneIm>
               <Name>OIS-Reech_IGNF_PVA_1-0__1971-06-21__C2844-0141_1971_FR2117_1123.tif</Name>
               <Residual>0.92830102962028338</Residual>
               <PercOk>95.8333333333333286</PercOk>
               <NbPts>360</NbPts>
               <NbPtsMul>88</NbPtsMul>
          </OneIm>
          <OneIm>
               <Name>OIS-Reech_IGNF_PVA_1-0__1971-06-21__C2844-0141_1971_FR2117_1124.tif</Name>
               <Residual>1.2692083998326118</Residual>
               <PercOk>95.1219512195121979</PercOk>
               <NbPts>287</NbPts>
               <NbPtsMul>92</NbPtsMul>
          </OneIm>
          <AverageResidual>1.2181531020238725</AverageResidual>
          <NumIter>6</NumIter>
          <NumEtape>0</NumEtape>
          <EvolMax>0.00448736931263046552</EvolMax>
          <EvolMoy>0.000438828091537086498</EvolMoy>
     </Iters>
     <Iters>
          <OneIm>
               <Name>Crop-IMG_PHR1A_P_201406121049025.tif</Name>
               <Residual>1.70958985420769016</Residual>
               <PercOk>88.5416666666666714</PercOk>
               <NbPts>384</NbPts>
               <NbPtsMul>0</NbPtsMul>
          </OneIm>
          <OneIm>
               <Name>Crop-IMG_PHR1A_P_201406121049386.tif</Name>
               <Residual>1.57712877689837261</Residual>
               <PercOk>86.5229110512129438</PercOk>
               <NbPts>371</NbPts>
               <NbPtsMul>0</NbPtsMul>
          </OneIm>
          <OneIm>
               <Name>OIS-Reech_IGNF_PVA_1-0__1971-06-21__C2844-0141_1971_FR2117_1066.tif</Name>
               <Residual>1.03786053987512528</Residual>
               <PercOk>95.5445544554455495</PercOk>
               <NbPts>202</NbPts>
               <NbPtsMul>55</NbPtsMul>
          </OneIm>
          <OneIm>
               <Name>OIS-Reech_IGNF_PVA_1-0__1971-06-21__C2844-0141_1971_FR2117_1067.tif</Name>
               <Residual>1.03239442481767174</Residual>
               <PercOk>96.4401294498381816</PercOk>
               <NbPts>309</NbPts>
               <NbPtsMul>86</NbPtsMul>
          </OneIm>
          <OneIm>
               <Name>OIS-Reech_IGNF_PVA_1-0__1971-06-21__C2844-0141_1971_FR2117_1068.tif</Name>
               <Residual>0.729620231772205252</Residual>
               <PercOk>92.1568627450980387</PercOk>
               <NbPts>153</NbPts>
               <NbPtsMul>32</NbPtsMul>
          </OneIm>
          <OneIm>
               <Name>OIS-Reech_IGNF_PVA_1-0__1971-06-21__C2844-0141_1971_FR2117_1122.tif</Name>
               <Residual>0.819771275933963262</Residual>
               <PercOk>91.4141414141414117</PercOk>
               <NbPts>198</NbPts>
               <NbPtsMul>49</NbPtsMul>
          </OneIm>
          <OneIm>
               <Name>OIS-Reech_IGNF_PVA_1-0__1971-06-21__C2844-0141_1971_FR2117_1123.tif</Name>
               <Residual>0.932481208542357276</Residual>
               <PercOk>95.5555555555555571</PercOk>
               <NbPts>360</NbPts>
               <NbPtsMul>88</NbPtsMul>
          </OneIm>
          <OneIm>
               <Name>OIS-Reech_IGNF_PVA_1-0__1971-06-21__C2844-0141_1971_FR2117_1124.tif</Name>
               <Residual>1.24856974567174994</Residual>
               <PercOk>95.1219512195121979</PercOk>
               <NbPts>287</NbPts>
               <NbPtsMul>92</NbPtsMul>
          </OneIm>
          <AverageResidual>1.1824679508714222</AverageResidual>
          <NumIter>7</NumIter>
          <NumEtape>0</NumEtape>
          <EvolMax>0.00320571916883720994</EvolMax>
          <EvolMoy>0.000319452448708149538</EvolMoy>
     </Iters>
     <Iters>
          <OneIm>
               <Name>Crop-IMG_PHR1A_P_201406121049025.tif</Name>
               <Residual>1.63791030791767533</Residual>
               <PercOk>87.5</PercOk>
               <NbPts>384</NbPts>
               <NbPtsMul>0</NbPtsMul>
          </OneIm>
          <OneIm>
               <Name>Crop-IMG_PHR1A_P_201406121049386.tif</Name>
               <Residual>1.59136542098010292</Residual>
               <PercOk>89.4878706199460936</PercOk>
               <NbPts>371</NbPts>
               <NbPtsMul>0</NbPtsMul>
          </OneIm>
          <OneIm>
               <Name>OIS-Reech_IGNF_PVA_1-0__1971-06-21__C2844-0141_1971_FR2117_1066.tif</Name>
               <Residual>1.02141164544553331</Residual>
               <PercOk>96.5346534653465369</PercOk>
               <NbPts>202</NbPts>
               <NbPtsMul>55</NbPtsMul>
          </OneIm>
          <OneIm>
               <Name>OIS-Reech_IGNF_PVA_1-0__1971-06-21__C2844-0141_1971_FR2117_1067.tif</Name>
               <Residual>0.987281838006652035</Residual>
               <PercOk>96.4401294498381816</PercOk>
               <NbPts>309</NbPts>
               <NbPtsMul>86</NbPtsMul>
          </OneIm>
          <OneIm>
               <Name>OIS-Reech_IGNF_PVA_1-0__1971-06-21__C2844-0141_1971_FR2117_1068.tif</Name>
               <Residual>0.845936854894642765</Residual>
               <PercOk>96.0784313725490193</PercOk>
               <NbPts>153</NbPts>
               <NbPtsMul>32</NbPtsMul>
          </OneIm>
          <OneIm>
               <Name>OIS-Reech_IGNF_PVA_1-0__1971-06-21__C2844-0141_1971_FR2117_1122.tif</Name>
               <Residual>0.826557753015698005</Residual>
               <PercOk>91.9191919191919169</PercOk>
               <NbPts>198</NbPts>
               <NbPtsMul>49</NbPtsMul>
          </OneIm>
          <OneIm>
               <Name>OIS-Reech_IGNF_PVA_1-0__1971-06-21__C2844-0141_1971_FR2117_1123.tif</Name>
               <Residual>0.92781467671483786</Residual>
               <PercOk>95.2777777777777715</PercOk>
               <NbPts>360</NbPts>
               <NbPtsMul>88</NbPtsMul>
          </OneIm>
          <OneIm>
               <Name>OIS-Reech_IGNF_PVA_1-0__1971-06-21__C2844-0141_1971_FR2117_1124.tif</Name>
               <Residual>1.22537695722693729</Residual>
               <PercOk>94.4250871080139405</PercOk>
               <NbPts>287</NbPts>
               <NbPtsMul>92</NbPtsMul>
          </OneIm>
          <AverageResidual>1.17230525569032706</AverageResidual>
          <NumIter>8</NumIter>
          <NumEtape>0</NumEtape>
          <EvolMax>0.00302806258349646706</EvolMax>
          <EvolMoy>0.000285162088117546725</EvolMoy>
     </Iters>
     <Iters>
          <OneIm>
               <Name>Crop-IMG_PHR1A_P_201406121049025.tif</Name>
               <Residual>1.63227297372696878</Residual>
               <PercOk>87.7604166666666714</PercOk>
               <NbPts>384</NbPts>
               <NbPtsMul>0</NbPtsMul>
          </OneIm>
          <OneIm>
               <Name>Crop-IMG_PHR1A_P_201406121049386.tif</Name>
               <Residual>1.58278406067091293</Residual>
               <PercOk>90.5660377358490507</PercOk>
               <NbPts>371</NbPts>
               <NbPtsMul>0</NbPtsMul>
          </OneIm>
          <OneIm>
               <Name>OIS-Reech_IGNF_PVA_1-0__1971-06-21__C2844-0141_1971_FR2117_1066.tif</Name>
               <Residual>1.01869238457786015</Residual>
               <PercOk>97.0297029702970235</PercOk>
               <NbPts>202</NbPts>
               <NbPtsMul>55</NbPtsMul>
          </OneIm>
          <OneIm>
               <Name>OIS-Reech_IGNF_PVA_1-0__1971-06-21__C2844-0141_1971_FR2117_1067.tif</Name>
               <Residual>1.00487055864206898</Residual>
               <PercOk>97.0873786407767057</PercOk>
               <NbPts>309</NbPts>
               <NbPtsMul>86</NbPtsMul>
          </OneIm>
          <OneIm>
               <Name>OIS-Reech_IGNF_PVA_1-0__1971-06-21__C2844-0141_1971_FR2117_1068.tif</Name>
               <Residual>0.848294711327741258</Residual>
               <PercOk>97.3856209150326748</PercOk>
               <NbPts>153</NbPts>
               <NbPtsMul>32</NbPtsMul>
          </OneIm>
          <OneIm>
               <Name>OIS-Reech_IGNF_PVA_1-0__1971-06-21__C2844-0141_1971_FR2117_1122.tif</Name>
               <Residual>0.82908920040234213</Residual>
               <PercOk>91.9191919191919169</PercOk>
               <NbPts>198</NbPts>
               <NbPtsMul>49</NbPtsMul>
          </OneIm>
          <OneIm>
               <Name>OIS-Reech_IGNF_PVA_1-0__1971-06-21__C2844-0141_1971_FR2117_1123.tif</Name>
               <Residual>0.91981240758183247</Residual>
               <PercOk>94.7222222222222285</PercOk>
               <NbPts>360</NbPts>
               <NbPtsMul>88</NbPtsMul>
          </OneIm>
          <OneIm>
               <Name>OIS-Reech_IGNF_PVA_1-0__1971-06-21__C2844-0141_1971_FR2117_1124.tif</Name>
               <Residual>1.21996224536592224</Residual>
               <PercOk>94.4250871080139405</PercOk>
               <NbPts>287</NbPts>
               <NbPtsMul>92</NbPtsMul>
          </OneIm>
          <AverageResidual>1.17038321834378789</AverageResidual>
          <NumIter>9</NumIter>
          <NumEtape>0</NumEtape>
          <EvolMax>0.00264080664412351179</EvolMax>
          <EvolMoy>0.000276860867649327089</EvolMoy>
     </Iters>
     <Iters>
          <OneIm>
               <Name>Crop-IMG_PHR1A_P_201406121049025.tif</Name>
               <Residual>1.62756370188460342</Residual>
               <PercOk>88.0208333333333286</PercOk>
               <NbPts>384</NbPts>
               <NbPtsMul>0</NbPtsMul>
          </OneIm>
          <OneIm>
               <Name>Crop-IMG_PHR1A_P_201406121049386.tif</Name>
               <Residual>1.54170047277226918</Residual>
               <PercOk>90.0269541778975793</PercOk>
               <NbPts>371</NbPts>
               <NbPtsMul>0</NbPtsMul>
          </OneIm>
          <OneIm>
               <Name>OIS-Reech_IGNF_PVA_1-0__1971-06-21__C2844-0141_1971_FR2117_1066.tif</Name>
               <Residual>1.0140451924111209</Residual>
               <PercOk>97.0297029702970235</PercOk>
               <NbPts>202</NbPts>
               <NbPtsMul>55</NbPtsMul>
          </OneIm>
          <OneIm>
               <Name>OIS-Reech_IGNF_PVA_1-0__1971-06-21__C2844-0141_1971_FR2117_1067.tif</Name>
               <Residual>0.996256015584808363</Residual>
               <PercOk>96.7637540453074365</PercOk>
               <NbPts>309</NbPts>
               <NbPtsMul>86</NbPtsMul>
          </OneIm>
          <OneIm>
               <Name>OIS-Reech_IGNF_PVA_1-0__1971-06-21__C2844-0141_1971_FR2117_1068.tif</Name>
               <Residual>0.744856729080209612</Residual>
               <PercOk>96.7320261437908471</PercOk>
               <NbPts>153</NbPts>
               <NbPtsMul>32</NbPtsMul>
          </OneIm>
          <OneIm>
               <Name>OIS-Reech_IGNF_PVA_1-0__1971-06-21__C2844-0141_1971_FR2117_1122.tif</Name>
               <Residual>0.840322991054559543</Residual>
               <PercOk>91.9191919191919169</PercOk>
               <NbPts>198</NbPts>
               <NbPtsMul>49</NbPtsMul>
          </OneIm>
          <OneIm>
               <Name>OIS-Reech_IGNF_PVA_1-0__1971-06-21__C2844-0141_1971_FR2117_1123.tif</Name>
               <Residual>0.911862379231805908</Residual>
               <PercOk>94.4444444444444429</PercOk>
               <NbPts>360</NbPts>
               <NbPtsMul>88</NbPtsMul>
          </OneIm>
          <OneIm>
               <Name>OIS-Reech_IGNF_PVA_1-0__1971-06-21__C2844-0141_1971_FR2117_1124.tif</Name>
               <Residual>1.22154035749617673</Residual>
               <PercOk>94.4250871080139405</PercOk>
               <NbPts>287</NbPts>
               <NbPtsMul>92</NbPtsMul>
          </OneIm>
          <AverageResidual>1.1527806476125837</AverageResidual>
          <NumIter>10</NumIter>
          <NumEtape>0</NumEtape>
          <EvolMax>0.00230988015082536852</EvolMax>
          <EvolMoy>0.000218567239014365479</EvolMoy>
     </Iters>
     <Iters>
          <OneIm>
               <Name>Crop-IMG_PHR1A_P_201406121049025.tif</Name>
               <Residual>1.61984664646833831</Residual>
               <PercOk>87.7604166666666714</PercOk>
               <NbPts>384</NbPts>
               <NbPtsMul>0</NbPtsMul>
          </OneIm>
          <OneIm>
               <Name>Crop-IMG_PHR1A_P_201406121049386.tif</Name>
               <Residual>1.53100604733864198</Residual>
               <PercOk>90.0269541778975793</PercOk>
               <NbPts>371</NbPts>
               <NbPtsMul>0</NbPtsMul>
          </OneIm>
          <OneIm>
               <Name>OIS-Reech_IGNF_PVA_1-0__1971-06-21__C2844-0141_1971_FR2117_1066.tif</Name>
               <Residual>1.01202214950963065</Residual>
               <PercOk>97.0297029702970235</PercOk>
               <NbPts>202</NbPts>
               <NbPtsMul>55</NbPtsMul>
          </OneIm>
          <OneIm>
               <Name>OIS-Reech_IGNF_PVA_1-0__1971-06-21__C2844-0141_1971_FR2117_1067.tif</Name>
               <Residual>0.997334588135940669</Residual>
               <PercOk>96.7637540453074365</PercOk>
               <NbPts>309</NbPts>
               <NbPtsMul>86</NbPtsMul>
          </OneIm>
          <OneIm>
               <Name>OIS-Reech_IGNF_PVA_1-0__1971-06-21__C2844-0141_1971_FR2117_1068.tif</Name>
               <Residual>0.718447803906063109</Residual>
               <PercOk>96.7320261437908471</PercOk>
               <NbPts>153</NbPts>
               <NbPtsMul>32</NbPtsMul>
          </OneIm>
          <OneIm>
               <Name>OIS-Reech_IGNF_PVA_1-0__1971-06-21__C2844-0141_1971_FR2117_1122.tif</Name>
               <Residual>0.849968844916316302</Residual>
               <PercOk>91.9191919191919169</PercOk>
               <NbPts>198</NbPts>
               <NbPtsMul>49</NbPtsMul>
          </OneIm>
          <OneIm>
               <Name>OIS-Reech_IGNF_PVA_1-0__1971-06-21__C2844-0141_1971_FR2117_1123.tif</Name>
               <Residual>0.886018003501056528</Residual>
               <PercOk>93.8888888888888857</PercOk>
               <NbPts>360</NbPts>
               <NbPtsMul>88</NbPtsMul>
          </OneIm>
          <OneIm>
               <Name>OIS-Reech_IGNF_PVA_1-0__1971-06-21__C2844-0141_1971_FR2117_1124.tif</Name>
               <Residual>1.22456591855383912</Residual>
               <PercOk>94.4250871080139405</PercOk>
               <NbPts>287</NbPts>
               <NbPtsMul>92</NbPtsMul>
          </OneIm>
          <AverageResidual>1.1461867028613848</AverageResidual>
          <NumIter>11</NumIter>
          <NumEtape>0</NumEtape>
          <EvolMax>0.0012046561614867449</EvolMax>
          <EvolMoy>0.000133591689577906565</EvolMoy>
     </Iters>
     <Iters>
          <OneIm>
               <Name>Crop-IMG_PHR1A_P_201406121049025.tif</Name>
               <Residual>1.62056038200063335</Residual>
               <PercOk>87.7604166666666714</PercOk>
               <NbPts>384</NbPts>
               <NbPtsMul>0</NbPtsMul>
          </OneIm>
          <OneIm>
               <Name>Crop-IMG_PHR1A_P_201406121049386.tif</Name>
               <Residual>1.51484026575252573</Residual>
               <PercOk>89.4878706199460936</PercOk>
               <NbPts>371</NbPts>
               <NbPtsMul>0</NbPtsMul>
          </OneIm>
          <OneIm>
               <Name>OIS-Reech_IGNF_PVA_1-0__1971-06-21__C2844-0141_1971_FR2117_1066.tif</Name>
               <Residual>1.01020544161037051</Residual>
               <PercOk>97.0297029702970235</PercOk>
               <NbPts>202</NbPts>
               <NbPtsMul>55</NbPtsMul>
          </OneIm>
          <OneIm>
               <Name>OIS-Reech_IGNF_PVA_1-0__1971-06-21__C2844-0141_1971_FR2117_1067.tif</Name>
               <Residual>0.989756309853453753</Residual>
               <PercOk>96.4401294498381816</PercOk>
               <NbPts>309</NbPts>
               <NbPtsMul>86</NbPtsMul>
          </OneIm>
          <OneIm>
               <Name>OIS-Reech_IGNF_PVA_1-0__1971-06-21__C2844-0141_1971_FR2117_1068.tif</Name>
               <Residual>0.710087451565612482</Residual>
               <PercOk>96.7320261437908471</PercOk>
               <NbPts>153</NbPts>
               <NbPtsMul>32</NbPtsMul>
          </OneIm>
          <OneIm>
               <Name>OIS-Reech_IGNF_PVA_1-0__1971-06-21__C2844-0141_1971_FR2117_1122.tif</Name>
               <Residual>0.839786344004083474</Residual>
               <PercOk>91.4141414141414117</PercOk>
               <NbPts>198</NbPts>
               <NbPtsMul>49</NbPtsMul>
          </OneIm>
          <OneIm>
               <Name>OIS-Reech_IGNF_PVA_1-0__1971-06-21__C2844-0141_1971_FR2117_1123.tif</Name>
               <Residual>0.878266606722207688</Residual>
               <PercOk>93.8888888888888857</PercOk>
               <NbPts>360</NbPts>
               <NbPtsMul>88</NbPtsMul>
          </OneIm>
          <OneIm>
               <Name>OIS-Reech_IGNF_PVA_1-0__1971-06-21__C2844-0141_1971_FR2117_1124.tif</Name>
               <Residual>1.22583953272571389</Residual>
               <PercOk>94.4250871080139405</PercOk>
               <NbPts>287</NbPts>
               <NbPtsMul>92</NbPtsMul>
          </OneIm>
          <AverageResidual>1.14042698443019463</AverageResidual>
          <NumIter>12</NumIter>
          <NumEtape>0</NumEtape>
          <EvolMax>0.000770811901260331275</EvolMax>
          <EvolMoy>7.43155914596367427e-05</EvolMoy>
     </Iters>
     <Iters>
          <OneIm>
               <Name>Crop-IMG_PHR1A_P_201406121049025.tif</Name>
               <Residual>1.62039343710188466</Residual>
               <PercOk>87.7604166666666714</PercOk>
               <NbPts>384</NbPts>
               <NbPtsMul>0</NbPtsMul>
          </OneIm>
          <OneIm>
               <Name>Crop-IMG_PHR1A_P_201406121049386.tif</Name>
               <Residual>1.50125216161152908</Residual>
               <PercOk>88.9487870619946079</PercOk>
               <NbPts>371</NbPts>
               <NbPtsMul>0</NbPtsMul>
          </OneIm>
          <OneIm>
               <Name>OIS-Reech_IGNF_PVA_1-0__1971-06-21__C2844-0141_1971_FR2117_1066.tif</Name>
               <Residual>1.00863515375069168</Residual>
               <PercOk>97.0297029702970235</PercOk>
               <NbPts>202</NbPts>
               <NbPtsMul>55</NbPtsMul>
          </OneIm>
          <OneIm>
               <Name>OIS-Reech_IGNF_PVA_1-0__1971-06-21__C2844-0141_1971_FR2117_1067.tif</Name>
               <Residual>0.981736391598936331</Residual>
               <PercOk>96.1165048543689267</PercOk>
               <NbPts>309</NbPts>
               <NbPtsMul>86</NbPtsMul>
          </OneIm>
          <OneIm>
               <Name>OIS-Reech_IGNF_PVA_1-0__1971-06-21__C2844-0141_1971_FR2117_1068.tif</Name>
               <Residual>0.707517922060554194</Residual>
               <PercOk>96.7320261437908471</PercOk>
               <NbPts>153</NbPts>
               <NbPtsMul>32</NbPtsMul>
          </OneIm>
          <OneIm>
               <Name>OIS-Reech_IGNF_PVA_1-0__1971-06-21__C2844-0141_1971_FR2117_1122.tif</Name>
               <Residual>0.826472814030784653</Residual>
               <PercOk>90.9090909090909065</PercOk>
               <NbPts>198</NbPts>
               <NbPtsMul>49</NbPtsMul>
          </OneIm>
          <OneIm>
               <Name>OIS-Reech_IGNF_PVA_1-0__1971-06-21__C2844-0141_1971_FR2117_1123.tif</Name>
               <Residual>0.877101106798410357</Residual>
               <PercOk>93.8888888888888857</PercOk>
               <NbPts>360</NbPts>
               <NbPtsMul>88</NbPtsMul>
          </OneIm>
          <OneIm>
               <Name>OIS-Reech_IGNF_PVA_1-0__1971-06-21__C2844-0141_1971_FR2117_1124.tif</Name>
               <Residual>1.22636756649129852</Residual>
               <PercOk>94.4250871080139405</PercOk>
               <NbPts>287</NbPts>
               <NbPtsMul>92</NbPtsMul>
          </OneIm>
          <AverageResidual>1.13564446690938237</AverageResidual>
          <NumIter>13</NumIter>
          <NumEtape>0</NumEtape>
          <EvolMax>0.000528398685520900806</EvolMax>
          <EvolMoy>3.79206293979994402e-05</EvolMoy>
     </Iters>
     <Iters>
          <OneIm>
               <Name>Crop-IMG_PHR1A_P_201406121049025.tif</Name>
               <Residual>1.61338895443786523</Residual>
               <PercOk>87.5</PercOk>
               <NbPts>384</NbPts>
               <NbPtsMul>0</NbPtsMul>
          </OneIm>
          <OneIm>
               <Name>Crop-IMG_PHR1A_P_201406121049386.tif</Name>
               <Residual>1.5020416309081337</Residual>
               <PercOk>88.9487870619946079</PercOk>
               <NbPts>371</NbPts>
               <NbPtsMul>0</NbPtsMul>
          </OneIm>
          <OneIm>
               <Name>OIS-Reech_IGNF_PVA_1-0__1971-06-21__C2844-0141_1971_FR2117_1066.tif</Name>
               <Residual>1.00786040245261521</Residual>
               <PercOk>97.0297029702970235</PercOk>
               <NbPts>202</NbPts>
               <NbPtsMul>55</NbPtsMul>
          </OneIm>
          <OneIm>
               <Name>OIS-Reech_IGNF_PVA_1-0__1971-06-21__C2844-0141_1971_FR2117_1067.tif</Name>
               <Residual>0.981354683672086781</Residual>
               <PercOk>96.1165048543689267</PercOk>
               <NbPts>309</NbPts>
               <NbPtsMul>86</NbPtsMul>
          </OneIm>
          <OneIm>
               <Name>OIS-Reech_IGNF_PVA_1-0__1971-06-21__C2844-0141_1971_FR2117_1068.tif</Name>
               <Residual>0.706422299331891601</Residual>
               <PercOk>96.7320261437908471</PercOk>
               <NbPts>153</NbPts>
               <NbPtsMul>32</NbPtsMul>
          </OneIm>
          <OneIm>
               <Name>OIS-Reech_IGNF_PVA_1-0__1971-06-21__C2844-0141_1971_FR2117_1122.tif</Name>
               <Residual>0.827102937032572538</Residual>
               <PercOk>90.9090909090909065</PercOk>
               <NbPts>198</NbPts>
               <NbPtsMul>49</NbPtsMul>
          </OneIm>
          <OneIm>
               <Name>OIS-Reech_IGNF_PVA_1-0__1971-06-21__C2844-0141_1971_FR2117_1123.tif</Name>
               <Residual>0.876169653635186618</Residual>
               <PercOk>93.8888888888888857</PercOk>
               <NbPts>360</NbPts>
               <NbPtsMul>88</NbPtsMul>
          </OneIm>
          <OneIm>
               <Name>OIS-Reech_IGNF_PVA_1-0__1971-06-21__C2844-0141_1971_FR2117_1124.tif</Name>
               <Residual>1.22658520957083894</Residual>
               <PercOk>94.4250871080139405</PercOk>
               <NbPts>287</NbPts>
               <NbPtsMul>92</NbPtsMul>
          </OneIm>
          <AverageResidual>1.13431195317970013</AverageResidual>
          <NumIter>14</NumIter>
          <NumEtape>0</NumEtape>
          <EvolMax>0.000332722144879054097</EvolMax>
          <EvolMoy>2.07419145262697427e-05</EvolMoy>
     </Iters>
     <Iters>
          <OneIm>
               <Name>Crop-IMG_PHR1A_P_201406121049025.tif</Name>
               <Residual>1.61322750406084947</Residual>
               <PercOk>87.5</PercOk>
               <NbPts>384</NbPts>
               <NbPtsMul>0</NbPtsMul>
          </OneIm>
          <OneIm>
               <Name>Crop-IMG_PHR1A_P_201406121049386.tif</Name>
               <Residual>1.50259407245360155</Residual>
               <PercOk>88.9487870619946079</PercOk>
               <NbPts>371</NbPts>
               <NbPtsMul>0</NbPtsMul>
          </OneIm>
          <OneIm>
               <Name>OIS-Reech_IGNF_PVA_1-0__1971-06-21__C2844-0141_1971_FR2117_1066.tif</Name>
               <Residual>1.00753914936662992</Residual>
               <PercOk>97.0297029702970235</PercOk>
               <NbPts>202</NbPts>
               <NbPtsMul>55</NbPtsMul>
          </OneIm>
          <OneIm>
               <Name>OIS-Reech_IGNF_PVA_1-0__1971-06-21__C2844-0141_1971_FR2117_1067.tif</Name>
               <Residual>0.981206007747358999</Residual>
               <PercOk>96.1165048543689267</PercOk>
               <NbPts>309</NbPts>
               <NbPtsMul>86</NbPtsMul>
          </OneIm>
          <OneIm>
               <Name>OIS-Reech_IGNF_PVA_1-0__1971-06-21__C2844-0141_1971_FR2117_1068.tif</Name>
               <Residual>0.706045664602156453</Residual>
               <PercOk>96.7320261437908471</PercOk>
               <NbPts>153</NbPts>
               <NbPtsMul>32</NbPtsMul>
          </OneIm>
          <OneIm>
               <Name>OIS-Reech_IGNF_PVA_1-0__1971-06-21__C2844-0141_1971_FR2117_1122.tif</Name>
               <Residual>0.827636625454752251</Residual>
               <PercOk>90.9090909090909065</PercOk>
               <NbPts>198</NbPts>
               <NbPtsMul>49</NbPtsMul>
          </OneIm>
          <OneIm>
               <Name>OIS-Reech_IGNF_PVA_1-0__1971-06-21__C2844-0141_1971_FR2117_1123.tif</Name>
               <Residual>0.875740398292234268</Residual>
               <PercOk>93.8888888888888857</PercOk>
               <NbPts>360</NbPts>
               <NbPtsMul>88</NbPtsMul>
          </OneIm>
          <OneIm>
               <Name>OIS-Reech_IGNF_PVA_1-0__1971-06-21__C2844-0141_1971_FR2117_1124.tif</Name>
               <Residual>1.22670611020723075</Residual>
               <PercOk>94.4250871080139405</PercOk>
               <NbPts>287</NbPts>
               <NbPtsMul>92</NbPtsMul>
          </OneIm>
          <AverageResidual>1.13431721113934136</AverageResidual>
          <NumIter>15</NumIter>
          <NumEtape>0</NumEtape>
          <EvolMax>0.000185788665833785911</EvolMax>
          <EvolMoy>1.13425352664458731e-05</EvolMoy>
     </Iters>
     <Iters>
          <OneIm>
               <Name>Crop-IMG_PHR1A_P_201406121049025.tif</Name>
               <Residual>1.61311782795162806</Residual>
               <PercOk>87.5</PercOk>
               <NbPts>384</NbPts>
               <NbPtsMul>0</NbPtsMul>
          </OneIm>
          <OneIm>
               <Name>Crop-IMG_PHR1A_P_201406121049386.tif</Name>
               <Residual>1.50298972513103712</Residual>
               <PercOk>88.9487870619946079</PercOk>
               <NbPts>371</NbPts>
               <NbPtsMul>0</NbPtsMul>
          </OneIm>
          <OneIm>
               <Name>OIS-Reech_IGNF_PVA_1-0__1971-06-21__C2844-0141_1971_FR2117_1066.tif</Name>
               <Residual>1.0074143144446861</Residual>
               <PercOk>97.0297029702970235</PercOk>
               <NbPts>202</NbPts>
               <NbPtsMul>55</NbPtsMul>
          </OneIm>
          <OneIm>
               <Name>OIS-Reech_IGNF_PVA_1-0__1971-06-21__C2844-0141_1971_FR2117_1067.tif</Name>
               <Residual>0.981154676868142395</Residual>
               <PercOk>96.1165048543689267</PercOk>
               <NbPts>309</NbPts>
               <NbPtsMul>86</NbPtsMul>
          </OneIm>
          <OneIm>
               <Name>OIS-Reech_IGNF_PVA_1-0__1971-06-21__C2844-0141_1971_FR2117_1068.tif</Name>
               <Residual>0.705909082728308435</Residual>
               <PercOk>96.7320261437908471</PercOk>
               <NbPts>153</NbPts>
               <NbPtsMul>32</NbPtsMul>
          </OneIm>
          <OneIm>
               <Name>OIS-Reech_IGNF_PVA_1-0__1971-06-21__C2844-0141_1971_FR2117_1122.tif</Name>
               <Residual>0.827984040243575303</Residual>
               <PercOk>90.9090909090909065</PercOk>
               <NbPts>198</NbPts>
               <NbPtsMul>49</NbPtsMul>
          </OneIm>
          <OneIm>
               <Name>OIS-Reech_IGNF_PVA_1-0__1971-06-21__C2844-0141_1971_FR2117_1123.tif</Name>
               <Residual>0.875550806240677715</Residual>
               <PercOk>93.8888888888888857</PercOk>
               <NbPts>360</NbPts>
               <NbPtsMul>88</NbPtsMul>
          </OneIm>
          <OneIm>
               <Name>OIS-Reech_IGNF_PVA_1-0__1971-06-21__C2844-0141_1971_FR2117_1124.tif</Name>
               <Residual>1.22678232360758677</Residual>
               <PercOk>94.4250871080139405</PercOk>
               <NbPts>287</NbPts>
               <NbPtsMul>92</NbPtsMul>
          </OneIm>
          <AverageResidual>1.13435690092416808</AverageResidual>
          <NumIter>16</NumIter>
          <NumEtape>0</NumEtape>
          <EvolMax>0.000104986063734119166</EvolMax>
          <EvolMoy>6.93073025407682953e-06</EvolMoy>
     </Iters>
     <Iters>
          <OneIm>
               <Name>Crop-IMG_PHR1A_P_201406121049025.tif</Name>
               <Residual>1.61304772560720533</Residual>
               <PercOk>87.5</PercOk>
               <NbPts>384</NbPts>
               <NbPtsMul>0</NbPtsMul>
          </OneIm>
          <OneIm>
               <Name>Crop-IMG_PHR1A_P_201406121049386.tif</Name>
               <Residual>1.49598897429100397</Residual>
               <PercOk>88.6792452830188722</PercOk>
               <NbPts>371</NbPts>
               <NbPtsMul>0</NbPtsMul>
          </OneIm>
          <OneIm>
               <Name>OIS-Reech_IGNF_PVA_1-0__1971-06-21__C2844-0141_1971_FR2117_1066.tif</Name>
               <Residual>1.00737937421157264</Residual>
               <PercOk>97.0297029702970235</PercOk>
               <NbPts>202</NbPts>
               <NbPtsMul>55</NbPtsMul>
          </OneIm>
          <OneIm>
               <Name>OIS-Reech_IGNF_PVA_1-0__1971-06-21__C2844-0141_1971_FR2117_1067.tif</Name>
               <Residual>0.981142928135047665</Residual>
               <PercOk>96.1165048543689267</PercOk>
               <NbPts>309</NbPts>
               <NbPtsMul>86</NbPtsMul>
          </OneIm>
          <OneIm>
               <Name>OIS-Reech_IGNF_PVA_1-0__1971-06-21__C2844-0141_1971_FR2117_1068.tif</Name>
               <Residual>0.705861373379760515</Residual>
               <PercOk>96.7320261437908471</PercOk>
               <NbPts>153</NbPts>
               <NbPtsMul>32</NbPtsMul>
          </OneIm>
          <OneIm>
               <Name>OIS-Reech_IGNF_PVA_1-0__1971-06-21__C2844-0141_1971_FR2117_1122.tif</Name>
               <Residual>0.828193817773544838</Residual>
               <PercOk>90.9090909090909065</PercOk>
               <NbPts>198</NbPts>
               <NbPtsMul>49</NbPtsMul>
          </OneIm>
          <OneIm>
               <Name>OIS-Reech_IGNF_PVA_1-0__1971-06-21__C2844-0141_1971_FR2117_1123.tif</Name>
               <Residual>0.875459754060588624</Residual>
               <PercOk>93.8888888888888857</PercOk>
               <NbPts>360</NbPts>
               <NbPtsMul>88</NbPtsMul>
          </OneIm>
          <OneIm>
               <Name>OIS-Reech_IGNF_PVA_1-0__1971-06-21__C2844-0141_1971_FR2117_1124.tif</Name>
               <Residual>1.22682712109182845</Residual>
               <PercOk>94.4250871080139405</PercOk>
               <NbPts>287</NbPts>
               <NbPtsMul>92</NbPtsMul>
          </OneIm>
          <AverageResidual>1.13319462524963654</AverageResidual>
          <NumIter>17</NumIter>
          <NumEtape>0</NumEtape>
          <EvolMax>6.10123882726337622e-05</EvolMax>
          <EvolMoy>4.61297269651390143e-06</EvolMoy>
     </Iters>
     <Iters>
          <OneIm>
               <Name>Crop-IMG_PHR1A_P_201406121049025.tif</Name>
               <Residual>1.61301608920194095</Residual>
               <PercOk>87.5</PercOk>
               <NbPts>384</NbPts>
               <NbPtsMul>0</NbPtsMul>
          </OneIm>
          <OneIm>
               <Name>Crop-IMG_PHR1A_P_201406121049386.tif</Name>
               <Residual>1.49621255008778742</Residual>
               <PercOk>88.6792452830188722</PercOk>
               <NbPts>371</NbPts>
               <NbPtsMul>0</NbPtsMul>
          </OneIm>
          <OneIm>
               <Name>OIS-Reech_IGNF_PVA_1-0__1971-06-21__C2844-0141_1971_FR2117_1066.tif</Name>
               <Residual>1.00736659677846974</Residual>
               <PercOk>97.0297029702970235</PercOk>
               <NbPts>202</NbPts>
               <NbPtsMul>55</NbPtsMul>
          </OneIm>
          <OneIm>
               <Name>OIS-Reech_IGNF_PVA_1-0__1971-06-21__C2844-0141_1971_FR2117_1067.tif</Name>
               <Residual>0.9811268748021299</Residual>
               <PercOk>96.1165048543689267</PercOk>
               <NbPts>309</NbPts>
               <NbPtsMul>86</NbPtsMul>
          </OneIm>
          <OneIm>
               <Name>OIS-Reech_IGNF_PVA_1-0__1971-06-21__C2844-0141_1971_FR2117_1068.tif</Name>
               <Residual>0.705827411904175417</Residual>
               <PercOk>96.7320261437908471</PercOk>
               <NbPts>153</NbPts>
               <NbPtsMul>32</NbPtsMul>
          </OneIm>
          <OneIm>
               <Name>OIS-Reech_IGNF_PVA_1-0__1971-06-21__C2844-0141_1971_FR2117_1122.tif</Name>
               <Residual>0.828303976169380118</Residual>
               <PercOk>90.9090909090909065</PercOk>
               <NbPts>198</NbPts>
               <NbPtsMul>49</NbPtsMul>
          </OneIm>
          <OneIm>
               <Name>OIS-Reech_IGNF_PVA_1-0__1971-06-21__C2844-0141_1971_FR2117_1123.tif</Name>
               <Residual>0.875380098276464347</Residual>
               <PercOk>93.8888888888888857</PercOk>
               <NbPts>360</NbPts>
               <NbPtsMul>88</NbPtsMul>
          </OneIm>
          <OneIm>
               <Name>OIS-Reech_IGNF_PVA_1-0__1971-06-21__C2844-0141_1971_FR2117_1124.tif</Name>
               <Residual>1.22685107825604911</Residual>
               <PercOk>94.4250871080139405</PercOk>
               <NbPts>287</NbPts>
               <NbPtsMul>92</NbPtsMul>
          </OneIm>
          <AverageResidual>1.13322570572009451</AverageResidual>
          <NumIter>18</NumIter>
          <NumEtape>0</NumEtape>
          <EvolMax>3.91116953475469355e-05</EvolMax>
          <EvolMoy>3.40474553644801288e-06</EvolMoy>
     </Iters>
     <Iters>
          <OneIm>
               <Name>Crop-IMG_PHR1A_P_201406121049025.tif</Name>
               <Residual>1.61299069305141285</Residual>
               <PercOk>87.5</PercOk>
               <NbPts>384</NbPts>
               <NbPtsMul>0</NbPtsMul>
          </OneIm>
          <OneIm>
               <Name>Crop-IMG_PHR1A_P_201406121049386.tif</Name>
               <Residual>1.49637984993186701</Residual>
               <PercOk>88.6792452830188722</PercOk>
               <NbPts>371</NbPts>
               <NbPtsMul>0</NbPtsMul>
          </OneIm>
          <OneIm>
               <Name>OIS-Reech_IGNF_PVA_1-0__1971-06-21__C2844-0141_1971_FR2117_1066.tif</Name>
               <Residual>1.00737162040732664</Residual>
               <PercOk>97.0297029702970235</PercOk>
               <NbPts>202</NbPts>
               <NbPtsMul>55</NbPtsMul>
          </OneIm>
          <OneIm>
               <Name>OIS-Reech_IGNF_PVA_1-0__1971-06-21__C2844-0141_1971_FR2117_1067.tif</Name>
               <Residual>0.981124568765585625</Residual>
               <PercOk>96.1165048543689267</PercOk>
               <NbPts>309</NbPts>
               <NbPtsMul>86</NbPtsMul>
          </OneIm>
          <OneIm>
               <Name>OIS-Reech_IGNF_PVA_1-0__1971-06-21__C2844-0141_1971_FR2117_1068.tif</Name>
               <Residual>0.705819329269098517</Residual>
               <PercOk>96.7320261437908471</PercOk>
               <NbPts>153</NbPts>
               <NbPtsMul>32</NbPtsMul>
          </OneIm>
          <OneIm>
               <Name>OIS-Reech_IGNF_PVA_1-0__1971-06-21__C2844-0141_1971_FR2117_1122.tif</Name>
               <Residual>0.828375755842351236</Residual>
               <PercOk>90.9090909090909065</PercOk>
               <NbPts>198</NbPts>
               <NbPtsMul>49</NbPtsMul>
          </OneIm>
          <OneIm>
               <Name>OIS-Reech_IGNF_PVA_1-0__1971-06-21__C2844-0141_1971_FR2117_1123.tif</Name>
               <Residual>0.875338182353677996</Residual>
               <PercOk>93.8888888888888857</PercOk>
               <NbPts>360</NbPts>
               <NbPtsMul>88</NbPtsMul>
          </OneIm>
          <OneIm>
               <Name>OIS-Reech_IGNF_PVA_1-0__1971-06-21__C2844-0141_1971_FR2117_1124.tif</Name>
               <Residual>1.22686437725235264</Residual>
               <PercOk>94.4250871080139405</PercOk>
               <NbPts>287</NbPts>
               <NbPtsMul>92</NbPtsMul>
          </OneIm>
          <AverageResidual>1.1332527897762068</AverageResidual>
          <NumIter>19</NumIter>
          <NumEtape>0</NumEtape>
          <EvolMax>2.42098499370858113e-05</EvolMax>
          <EvolMoy>2.47832852331255164e-06</EvolMoy>
     </Iters>
     <Iters>
          <OneIm>
               <Name>Crop-IMG_PHR1A_P_201406121049025.tif</Name>
               <Residual>1.61297130465720762</Residual>
               <PercOk>87.5</PercOk>
               <NbPts>384</NbPts>
               <NbPtsMul>0</NbPtsMul>
          </OneIm>
          <OneIm>
               <Name>Crop-IMG_PHR1A_P_201406121049386.tif</Name>
               <Residual>1.49650808205035601</Residual>
               <PercOk>88.6792452830188722</PercOk>
               <NbPts>371</NbPts>
               <NbPtsMul>0</NbPtsMul>
          </OneIm>
          <OneIm>
               <Name>OIS-Reech_IGNF_PVA_1-0__1971-06-21__C2844-0141_1971_FR2117_1066.tif</Name>
               <Residual>1.00738175809049624</Residual>
               <PercOk>97.0297029702970235</PercOk>
               <NbPts>202</NbPts>
               <NbPtsMul>55</NbPtsMul>
          </OneIm>
          <OneIm>
               <Name>OIS-Reech_IGNF_PVA_1-0__1971-06-21__C2844-0141_1971_FR2117_1067.tif</Name>
               <Residual>0.981125199058085706</Residual>
               <PercOk>96.1165048543689267</PercOk>
               <NbPts>309</NbPts>
               <NbPtsMul>86</NbPtsMul>
          </OneIm>
          <OneIm>
               <Name>OIS-Reech_IGNF_PVA_1-0__1971-06-21__C2844-0141_1971_FR2117_1068.tif</Name>
               <Residual>0.705819049635836526</Residual>
               <PercOk>96.7320261437908471</PercOk>
               <NbPts>153</NbPts>
               <NbPtsMul>32</NbPtsMul>
          </OneIm>
          <OneIm>
               <Name>OIS-Reech_IGNF_PVA_1-0__1971-06-21__C2844-0141_1971_FR2117_1122.tif</Name>
               <Residual>0.828419046362824818</Residual>
               <PercOk>90.9090909090909065</PercOk>
               <NbPts>198</NbPts>
               <NbPtsMul>49</NbPtsMul>
          </OneIm>
          <OneIm>
               <Name>OIS-Reech_IGNF_PVA_1-0__1971-06-21__C2844-0141_1971_FR2117_1123.tif</Name>
               <Residual>0.875313385060923044</Residual>
               <PercOk>93.8888888888888857</PercOk>
               <NbPts>360</NbPts>
               <NbPtsMul>88</NbPtsMul>
          </OneIm>
          <OneIm>
               <Name>OIS-Reech_IGNF_PVA_1-0__1971-06-21__C2844-0141_1971_FR2117_1124.tif</Name>
               <Residual>1.22687141711402692</Residual>
               <PercOk>94.4250871080139405</PercOk>
               <NbPts>287</NbPts>
               <NbPtsMul>92</NbPtsMul>
          </OneIm>
          <AverageResidual>1.13327419318172939</AverageResidual>
          <NumIter>20</NumIter>
          <NumEtape>0</NumEtape>
          <EvolMax>1.55798175289825713e-05</EvolMax>
          <EvolMoy>1.87919556628792974e-06</EvolMoy>
     </Iters>
     <Iters>
          <OneIm>
               <Name>Crop-IMG_PHR1A_P_201406121049025.tif</Name>
               <Residual>1.61295666448370367</Residual>
               <PercOk>87.5</PercOk>
               <NbPts>384</NbPts>
               <NbPtsMul>0</NbPtsMul>
          </OneIm>
          <OneIm>
               <Name>Crop-IMG_PHR1A_P_201406121049386.tif</Name>
               <Residual>1.4966074319331748</Residual>
               <PercOk>88.6792452830188722</PercOk>
               <NbPts>371</NbPts>
               <NbPtsMul>0</NbPtsMul>
          </OneIm>
          <OneIm>
               <Name>OIS-Reech_IGNF_PVA_1-0__1971-06-21__C2844-0141_1971_FR2117_1066.tif</Name>
               <Residual>1.00739198507949435</Residual>
               <PercOk>97.0297029702970235</PercOk>
               <NbPts>202</NbPts>
               <NbPtsMul>55</NbPtsMul>
          </OneIm>
          <OneIm>
               <Name>OIS-Reech_IGNF_PVA_1-0__1971-06-21__C2844-0141_1971_FR2117_1067.tif</Name>
               <Residual>0.98112588864648953</Residual>
               <PercOk>96.1165048543689267</PercOk>
               <NbPts>309</NbPts>
               <NbPtsMul>86</NbPtsMul>
          </OneIm>
          <OneIm>
               <Name>OIS-Reech_IGNF_PVA_1-0__1971-06-21__C2844-0141_1971_FR2117_1068.tif</Name>
               <Residual>0.705821146034864233</Residual>
               <PercOk>96.7320261437908471</PercOk>
               <NbPts>153</NbPts>
               <NbPtsMul>32</NbPtsMul>
          </OneIm>
          <OneIm>
               <Name>OIS-Reech_IGNF_PVA_1-0__1971-06-21__C2844-0141_1971_FR2117_1122.tif</Name>
               <Residual>0.828444396819315254</Residual>
               <PercOk>90.9090909090909065</PercOk>
               <NbPts>198</NbPts>
               <NbPtsMul>49</NbPtsMul>
          </OneIm>
          <OneIm>
               <Name>OIS-Reech_IGNF_PVA_1-0__1971-06-21__C2844-0141_1971_FR2117_1123.tif</Name>
               <Residual>0.875297162403117945</Residual>
               <PercOk>93.8888888888888857</PercOk>
               <NbPts>360</NbPts>
               <NbPtsMul>88</NbPtsMul>
          </OneIm>
          <OneIm>
               <Name>OIS-Reech_IGNF_PVA_1-0__1971-06-21__C2844-0141_1971_FR2117_1124.tif</Name>
               <Residual>1.22687481854799141</Residual>
               <PercOk>94.4250871080139405</PercOk>
               <NbPts>287</NbPts>
               <NbPtsMul>92</NbPtsMul>
          </OneIm>
          <AverageResidual>1.13329057281794343</AverageResidual>
          <NumIter>21</NumIter>
          <NumEtape>0</NumEtape>
          <EvolMax>1.05281120689847361e-05</EvolMax>
          <EvolMoy>1.45350406567312709e-06</EvolMoy>
     </Iters>
     <Iters>
          <OneIm>
               <Name>Crop-IMG_PHR1A_P_201406121049025.tif</Name>
               <Residual>1.61294559648193414</Residual>
               <PercOk>87.5</PercOk>
               <NbPts>384</NbPts>
               <NbPtsMul>0</NbPtsMul>
          </OneIm>
          <OneIm>
               <Name>Crop-IMG_PHR1A_P_201406121049386.tif</Name>
               <Residual>1.49668473094280907</Residual>
               <PercOk>88.6792452830188722</PercOk>
               <NbPts>371</NbPts>
               <NbPtsMul>0</NbPtsMul>
          </OneIm>
          <OneIm>
               <Name>OIS-Reech_IGNF_PVA_1-0__1971-06-21__C2844-0141_1971_FR2117_1066.tif</Name>
               <Residual>1.00740068270139327</Residual>
               <PercOk>97.0297029702970235</PercOk>
               <NbPts>202</NbPts>
               <NbPtsMul>55</NbPtsMul>
          </OneIm>
          <OneIm>
               <Name>OIS-Reech_IGNF_PVA_1-0__1971-06-21__C2844-0141_1971_FR2117_1067.tif</Name>
               <Residual>0.981126030520102499</Residual>
               <PercOk>96.1165048543689267</PercOk>
               <NbPts>309</NbPts>
               <NbPtsMul>86</NbPtsMul>
          </OneIm>
          <OneIm>
               <Name>OIS-Reech_IGNF_PVA_1-0__1971-06-21__C2844-0141_1971_FR2117_1068.tif</Name>
               <Residual>0.705823723226709387</Residual>
               <PercOk>96.7320261437908471</PercOk>
               <NbPts>153</NbPts>
               <NbPtsMul>32</NbPtsMul>
          </OneIm>
          <OneIm>
               <Name>OIS-Reech_IGNF_PVA_1-0__1971-06-21__C2844-0141_1971_FR2117_1122.tif</Name>
               <Residual>0.82845906742429376</Residual>
               <PercOk>90.9090909090909065</PercOk>
               <NbPts>198</NbPts>
               <NbPtsMul>49</NbPtsMul>
          </OneIm>
          <OneIm>
               <Name>OIS-Reech_IGNF_PVA_1-0__1971-06-21__C2844-0141_1971_FR2117_1123.tif</Name>
               <Residual>0.875285755897193152</Residual>
               <PercOk>93.8888888888888857</PercOk>
               <NbPts>360</NbPts>
               <NbPtsMul>88</NbPtsMul>
          </OneIm>
          <OneIm>
               <Name>OIS-Reech_IGNF_PVA_1-0__1971-06-21__C2844-0141_1971_FR2117_1124.tif</Name>
               <Residual>1.22687612562424131</Residual>
               <PercOk>94.4250871080139405</PercOk>
               <NbPts>287</NbPts>
               <NbPtsMul>92</NbPtsMul>
          </OneIm>
          <AverageResidual>1.13330296264335217</AverageResidual>
          <NumIter>22</NumIter>
          <NumEtape>0</NumEtape>
          <EvolMax>8.05564171738601666e-06</EvolMax>
          <EvolMoy>1.13276675153803169e-06</EvolMoy>
     </Iters>
     <Iters>
          <OneIm>
               <Name>Crop-IMG_PHR1A_P_201406121049025.tif</Name>
               <Residual>1.61293716080681016</Residual>
               <PercOk>87.5</PercOk>
               <NbPts>384</NbPts>
               <NbPtsMul>0</NbPtsMul>
          </OneIm>
          <OneIm>
               <Name>Crop-IMG_PHR1A_P_201406121049386.tif</Name>
               <Residual>1.49674494482567511</Residual>
               <PercOk>88.6792452830188722</PercOk>
               <NbPts>371</NbPts>
               <NbPtsMul>0</NbPtsMul>
          </OneIm>
          <OneIm>
               <Name>OIS-Reech_IGNF_PVA_1-0__1971-06-21__C2844-0141_1971_FR2117_1066.tif</Name>
               <Residual>1.00740748463173868</Residual>
               <PercOk>97.0297029702970235</PercOk>
               <NbPts>202</NbPts>
               <NbPtsMul>55</NbPtsMul>
          </OneIm>
          <OneIm>
               <Name>OIS-Reech_IGNF_PVA_1-0__1971-06-21__C2844-0141_1971_FR2117_1067.tif</Name>
               <Residual>0.981125676239446465</Residual>
               <PercOk>96.1165048543689267</PercOk>
               <NbPts>309</NbPts>
               <NbPtsMul>86</NbPtsMul>
          </OneIm>
          <OneIm>
               <Name>OIS-Reech_IGNF_PVA_1-0__1971-06-21__C2844-0141_1971_FR2117_1068.tif</Name>
               <Residual>0.705826147627878542</Residual>
               <PercOk>96.7320261437908471</PercOk>
               <NbPts>153</NbPts>
               <NbPtsMul>32</NbPtsMul>
          </OneIm>
          <OneIm>
               <Name>OIS-Reech_IGNF_PVA_1-0__1971-06-21__C2844-0141_1971_FR2117_1122.tif</Name>
               <Residual>0.82846751974658206</Residual>
               <PercOk>90.9090909090909065</PercOk>
               <NbPts>198</NbPts>
               <NbPtsMul>49</NbPtsMul>
          </OneIm>
          <OneIm>
               <Name>OIS-Reech_IGNF_PVA_1-0__1971-06-21__C2844-0141_1971_FR2117_1123.tif</Name>
               <Residual>0.875277349611167543</Residual>
               <PercOk>93.8888888888888857</PercOk>
               <NbPts>360</NbPts>
               <NbPtsMul>88</NbPtsMul>
          </OneIm>
          <OneIm>
               <Name>OIS-Reech_IGNF_PVA_1-0__1971-06-21__C2844-0141_1971_FR2117_1124.tif</Name>
               <Residual>1.22687627073658234</Residual>
               <PercOk>94.4250871080139405</PercOk>
               <NbPts>287</NbPts>
               <NbPtsMul>92</NbPtsMul>
          </OneIm>
          <AverageResidual>1.13331228880383095</AverageResidual>
          <NumIter>23</NumIter>
          <NumEtape>0</NumEtape>
          <EvolMax>6.40368508639028027e-06</EvolMax>
          <EvolMoy>8.85117238248530756e-07</EvolMoy>
     </Iters>
     <Iters>
          <OneIm>
               <Name>Crop-IMG_PHR1A_P_201406121049025.tif</Name>
               <Residual>1.61293066554189601</Residual>
               <PercOk>87.5</PercOk>
               <NbPts>384</NbPts>
               <NbPtsMul>0</NbPtsMul>
          </OneIm>
          <OneIm>
               <Name>Crop-IMG_PHR1A_P_201406121049386.tif</Name>
               <Residual>1.49679187939842295</Residual>
               <PercOk>88.6792452830188722</PercOk>
               <NbPts>371</NbPts>
               <NbPtsMul>0</NbPtsMul>
          </OneIm>
          <OneIm>
               <Name>OIS-Reech_IGNF_PVA_1-0__1971-06-21__C2844-0141_1971_FR2117_1066.tif</Name>
               <Residual>1.00741272489057643</Residual>
               <PercOk>97.0297029702970235</PercOk>
               <NbPts>202</NbPts>
               <NbPtsMul>55</NbPtsMul>
          </OneIm>
          <OneIm>
               <Name>OIS-Reech_IGNF_PVA_1-0__1971-06-21__C2844-0141_1971_FR2117_1067.tif</Name>
               <Residual>0.981125037576383918</Residual>
               <PercOk>96.1165048543689267</PercOk>
               <NbPts>309</NbPts>
               <NbPtsMul>86</NbPtsMul>
          </OneIm>
          <OneIm>
               <Name>OIS-Reech_IGNF_PVA_1-0__1971-06-21__C2844-0141_1971_FR2117_1068.tif</Name>
               <Residual>0.705828237820921189</Residual>
               <PercOk>96.7320261437908471</PercOk>
               <NbPts>153</NbPts>
               <NbPtsMul>32</NbPtsMul>
          </OneIm>
          <OneIm>
               <Name>OIS-Reech_IGNF_PVA_1-0__1971-06-21__C2844-0141_1971_FR2117_1122.tif</Name>
               <Residual>0.828472404490001257</Residual>
               <PercOk>90.9090909090909065</PercOk>
               <NbPts>198</NbPts>
               <NbPtsMul>49</NbPtsMul>
          </OneIm>
          <OneIm>
               <Name>OIS-Reech_IGNF_PVA_1-0__1971-06-21__C2844-0141_1971_FR2117_1123.tif</Name>
               <Residual>0.875271010828689522</Residual>
               <PercOk>93.8888888888888857</PercOk>
               <NbPts>360</NbPts>
               <NbPtsMul>88</NbPtsMul>
          </OneIm>
          <OneIm>
               <Name>OIS-Reech_IGNF_PVA_1-0__1971-06-21__C2844-0141_1971_FR2117_1124.tif</Name>
               <Residual>1.22687585581876912</Residual>
               <PercOk>94.4250871080139405</PercOk>
               <NbPts>287</NbPts>
               <NbPtsMul>92</NbPtsMul>
          </OneIm>
          <AverageResidual>1.13331933573486632</AverageResidual>
          <NumIter>24</NumIter>
          <NumEtape>0</NumEtape>
          <EvolMax>5.04673222412403305e-06</EvolMax>
          <EvolMoy>6.92245412432148376e-07</EvolMoy>
     </Iters>
</XmlSauvExportAperoGlob>
