<?xml version="1.0" ?>
<ExportAPERO>
     <OrientationConique>
          <OrIntImaM2C>
               <I00>-1.38851892946452869e-13 1.63918261680211965e-13</I00>
               <V10>39.0833333333333357 -2.09982922682190127e-15</V10>
               <V01>9.71782453889560477e-16 39.0833333333333286</V01>
          </OrIntImaM2C>
          <TypeProj>eProjStenope</TypeProj>
          <FileInterne>Ori-SmallPerturb/AutoCal500.xml</FileInterne>
          <RelativeNameFI>true</RelativeNameFI>
          <Externe>
               <AltiSol>-14.834662832240074</AltiSol>
               <Profondeur>14.7126065207243144</Profondeur>
               <Time>-1.00000000000000002e+30</Time>
               <KnownConv>eConvApero_DistM2C</KnownConv>
               <Centre>0.110065223324519956 1.51267288890385188 -0.111283696564057233</Centre>
               <IncCentre>1 1 1</IncCentre>
               <ParamRotation>
                    <CodageMatr>
                         <L1>0.999295124580943717 0.0356897618164456823 -0.0116402272418386233</L1>
                         <L2>0.0353205436323175623 -0.998910021117487057 -0.030516043462076866</L2>
                         <L3>-0.0127166499626991947 0.0300833942989681448 -0.999466495787217024</L3>
                    </CodageMatr>
               </ParamRotation>
          </Externe>
          <Verif>
               <Tol>0.00100000000000000002</Tol>
               <ShowMes>true</ShowMes>
               <Appuis>
                    <Num>0</Num>
                    <Im>5.64011317501564946 6.60978055009456433</Im>
                    <Ter>-2.79077929909312639 2.53793172107899645 -17.4721272347698147</Ter>
               </Appuis>
               <Appuis>
                    <Num>1</Num>
                    <Im>9.37716472149279312 13.3454647064206195</Im>
                    <Ter>-1.03408636097437689 1.00227674495270169 -11.1242789329301495</Ter>
               </Appuis>
               <Appuis>
                    <Num>2</Num>
                    <Im>32.2804584502955905 19.7019910812286554</Im>
                    <Ter>4.29673011667081539 -0.611875116141679554 -15.8576173924324468</Ter>
               </Appuis>
               <Appuis>
                    <Num>3</Num>
                    <Im>25.1828978061966815 9.18528413773431751</Im>
                    <Ter>2.24046547459149803 1.93569113150807715 -14.7345072154114778</Ter>
               </Appuis>
               <Appuis>
                    <Num>4</Num>
                    <Im>5.14261007308977014 1.17662778496761766</Im>
                    <Ter>-1.71994140963316422 3.0067142450196167 -10.4065878925421931</Ter>
               </Appuis>
               <Appuis>
                    <Num>5</Num>
                    <Im>34.4187669753320762 9.3162553310514209</Im>
                    <Ter>4.126882546069365 1.9530596399997866 -13.8369388921737055</Ter>
               </Appuis>
               <Appuis>
                    <Num>6</Num>
                    <Im>16.3239959477496654 0.518612579210432689</Im>
                    <Ter>0.107699598218025466 4.09094496634208848 -16.0868826619582634</Ter>
               </Appuis>
               <Appuis>
                    <Num>7</Num>
                    <Im>11.5331200361214528 22.015976429028985</Im>
                    <Ter>-1.21411153181405762 -2.26021979784565907 -20.572158545216471</Ter>
               </Appuis>
               <Appuis>
                    <Num>8</Num>
                    <Im>30.8687860965722081 10.6287610530854089</Im>
                    <Ter>3.31274756539553161 1.63690926434473893 -13.6252014549459357</Ter>
               </Appuis>
               <Appuis>
                    <Num>9</Num>
                    <Im>23.0047123432456786 18.4230508804485318</Im>
                    <Ter>1.02606604257639056 0.573883141309440514 -7.95033381232577785</Ter>
               </Appuis>
          </Verif>
          <ConvOri>
               <KnownConv>eConvApero_DistM2C</KnownConv>
          </ConvOri>
     </OrientationConique>
</ExportAPERO>
