<FitsParam>
   <!-- Quick for overlap dec -->
   <OverLap> 
         <KindOf> eTPR_GrayMax    </KindOf>
         <BinIndexed>  <!-- Quick one, for indexation -->
            <PrefName>  Save_CompCB_BM2_NBB16_PdsW3000_   </PrefName>
         </BinIndexed>  
         <BinDecision>  <!-- Longer one making the decision -->
            <PrefName>  Save_CompCB_NBB80_PdsW100000_   </PrefName>
         </BinDecision>  
   </OverLap> 
   <SeuilOL>  
   </SeuilOL>

   <SeuilGen>  
        <SeuilCorrDR > 0.6 </SeuilCorrDR> 
        <SeuilInc    > 0.03  </SeuilInc> 
        <SeuilCorrLP > 0.9 </SeuilCorrLP>
   </SeuilGen>
   <GenLabs> 
         <KindOf> eTPR_GrayMax    </KindOf>
         <BinIndexed>  <!-- Quick one, for indexation -->
              <PrefName>  Save_CompCB_BM2_NBB16_PdsW300_   </PrefName>
         </BinIndexed>  
         <BinDecision>  <!-- Longer one making the decision -->
              <PrefName>  Save_CompCB_NBB80_PdsW300_  </PrefName>
         </BinDecision>  
   </GenLabs> 
   <GenLabs> 
         <KindOf> eTPR_GrayMin    </KindOf>
         <BinIndexed>  <!-- Quick one, for indexation -->
              <PrefName>  Save_CompCB_BM2_NBB16_PdsW300_   </PrefName>
         </BinIndexed>  
         <BinDecision>  <!-- Longer one making the decision -->
              <PrefName>  Save_CompCB_NBB80_PdsW300_  </PrefName>
         </BinDecision>  
   </GenLabs> 
   <GenLabs> 
         <KindOf> eTPR_LaplMax    </KindOf>
         <BinIndexed>  <!-- Quick one, for indexation -->
              <PrefName>  Save_CompCB_BM2_NBB16_PdsW300_   </PrefName>
         </BinIndexed>  
         <BinDecision>  <!-- Longer one making the decision -->
              <PrefName>  Save_CompCB_NBB80_PdsW300_  </PrefName>
         </BinDecision>  
   </GenLabs> 
   <GenLabs> 
         <KindOf> eTPR_LaplMin    </KindOf>
         <BinIndexed>  <!-- Quick one, for indexation -->
              <PrefName>  Save_CompCB_BM2_NBB16_PdsW300_   </PrefName>
         </BinIndexed>  
         <BinDecision>  <!-- Longer one making the decision -->
              <PrefName>  Save_CompCB_NBB80_PdsW300_  </PrefName>
         </BinDecision>  
   </GenLabs> 
</FitsParam>

